technicalmethods/__init__.py
technicalmethods/methods.py
technicalmethods-0.2.7.dist-info/LICENSE
technicalmethods-0.2.7.dist-info/METADATA
technicalmethods-0.2.7.dist-info/WHEEL
technicalmethods-0.2.7.dist-info/top_level.txt
technicalmethods-0.2.7.dist-info/RECORD
