Metadata-Version: 2.1
Name: technicalmethods
Version: 0.2.7
Summary: Technical Analysis tools
Home-page: https://github.com/GBERESEARCH/technicalmethods
Author: GBERESEARCH
Author-email: gberesearch@gmail.com
License: MIT
License-File: LICENSE
Requires-Dist: numpy >=1.16.2
Requires-Dist: pandas >=1.0.0
Requires-Dist: scipy >=1.7.0
